{"Leader": {"MegaDraftGroupId": 1, "MegaContestKey": "90080931", "MegaEntryKey": "2160590739", "UserName": "ClaySweet", "UserKey": "10290690", "UserMegaEntryCount": 0, "UserMegaEntryIndex": 0, "TimeRemainingOpponent": 0, "Rank": 1, "FantasyPoints": 1449.16, "FantasyPointsOpponent": 1380.96, "RankScore": 0, "RankScoreOpponent": 0, "UserNameOpponent": "sansbacon", "WinningValue": 2.7, "Winnings": [{"value": 2.7, "description": "Cash"}], "UpdateStatus": {"lastUpdateTime": "2020-10-30T00:21:09.0112827+00:00"}}, "LastWinningMegaEntry": {"MegaDraftGroupId": 1, "MegaContestKey": "90080931", "MegaEntryKey": "2160590739", "UserName": "ClaySweet", "UserKey": "10290690", "UserMegaEntryCount": 0, "UserMegaEntryIndex": 0, "TimeRemainingOpponent": 0, "Rank": 1, "FantasyPoints": 1449.16, "FantasyPointsOpponent": 1380.96, "RankScore": 0, "RankScoreOpponent": 0, "UserNameOpponent": "sansbacon", "WinningValue": 2.7, "Winnings": [{"value": 2.7, "description": "Cash"}], "UpdateStatus": {"lastUpdateTime": "2020-10-30T00:21:09.0112827+00:00"}}, "Leaderboard": [{"MegaDraftGroupId": 1, "MegaContestKey": "90080931", "MegaEntryKey": "2160590739", "UserName": "ClaySweet", "UserKey": "10290690", "UserMegaEntryCount": 0, "UserMegaEntryIndex": 0, "TimeRemainingOpponent": 0, "Rank": 1, "FantasyPoints": 1449.16, "FantasyPointsOpponent": 1380.96, "RankScore": 0, "RankScoreOpponent": 0, "UserNameOpponent": "sansbacon", "WinningValue": 2.7, "Winnings": [{"value": 2.7, "description": "Cash"}], "UpdateStatus": {"lastUpdateTime": "2020-10-30T00:21:09.0112827+00:00"}}, {"MegaDraftGroupId": 1, "MegaContestKey": "90080931", "MegaEntryKey": "2160615572", "UserName": "sansbacon", "UserKey": "725157", "UserMegaEntryCount": 0, "UserMegaEntryIndex": 0, "TimeRemainingOpponent": 0, "Rank": 2, "FantasyPoints": 1380.96, "FantasyPointsOpponent": 1449.16, "RankScore": 0, "RankScoreOpponent": 0, "UserNameOpponent": "ClaySweet", "WinningValue": 0, "UpdateStatus": {"lastUpdateTime": "2020-10-30T00:21:09.0123517+00:00"}}, {"MegaDraftGroupId": 1, "MegaContestKey": "90080931", "MegaEntryKey": "2160616745", "UserName": "cgiannell", "UserKey": "6738211", "UserMegaEntryCount": 0, "UserMegaEntryIndex": 0, "TimeRemainingOpponent": 0, "Rank": 3, "FantasyPoints": 1161.14, "FantasyPointsOpponent": 1449.16, "RankScore": 0, "RankScoreOpponent": 0, "UserNameOpponent": "ClaySweet", "WinningValue": 0, "UpdateStatus": {"lastUpdateTime": "2020-10-30T00:21:09.0094639+00:00"}}], "UpdateStatus": {"lastUpdateTime": "2020-10-30T00:21:09.0132326+00:00"}}