{"Leader": {"MegaDraftGroupId": 2, "MegaContestKey": "91482394", "MegaEntryKey": "2198813529", "UserName": "sansbacon", "UserKey": "725157", "UserMegaEntryCount": 0, "UserMegaEntryIndex": 0, "TimeRemainingOpponent": 0, "Rank": 1, "FantasyPoints": 1188.82, "FantasyPointsOpponent": 1074.38, "RankScore": 0, "RankScoreOpponent": 0, "UserNameOpponent": "panic97", "WinningValue": 160.07, "Winnings": [{"value": 160, "description": "Prize"}], "UpdateStatus": {"lastUpdateTime": "2020-10-30T00:22:13.1092474+00:00"}}, "LastWinningMegaEntry": {"MegaDraftGroupId": 2, "MegaContestKey": "91482394", "MegaEntryKey": "2198813201", "UserName": "theprof02", "UserKey": "7686051", "UserMegaEntryCount": 0, "UserMegaEntryIndex": 0, "TimeRemainingOpponent": 0, "Rank": 3, "FantasyPoints": 1049.5, "FantasyPointsOpponent": 1188.82, "RankScore": 0, "RankScoreOpponent": 0, "UserNameOpponent": "sansbacon", "WinningValue": 20, "Winnings": [{"value": 20, "description": "Cash"}], "UpdateStatus": {"lastUpdateTime": "2020-10-30T00:22:13.1085953+00:00"}}, "Leaderboard": [{"MegaDraftGroupId": 2, "MegaContestKey": "91482394", "MegaEntryKey": "2198813529", "UserName": "sansbacon", "UserKey": "725157", "UserMegaEntryCount": 0, "UserMegaEntryIndex": 0, "TimeRemainingOpponent": 0, "Rank": 1, "FantasyPoints": 1188.82, "FantasyPointsOpponent": 1074.38, "RankScore": 0, "RankScoreOpponent": 0, "UserNameOpponent": "panic97", "WinningValue": 160.07, "Winnings": [{"value": 160, "description": "Prize"}], "UpdateStatus": {"lastUpdateTime": "2020-10-30T00:22:13.1092474+00:00"}}, {"MegaDraftGroupId": 2, "MegaContestKey": "91482394", "MegaEntryKey": "2198813081", "UserName": "panic97", "UserKey": "6108753", "UserMegaEntryCount": 0, "UserMegaEntryIndex": 0, "TimeRemainingOpponent": 0, "Rank": 2, "FantasyPoints": 1074.38, "FantasyPointsOpponent": 1188.82, "RankScore": 0, "RankScoreOpponent": 0, "UserNameOpponent": "sansbacon", "WinningValue": 30, "Winnings": [{"value": 30, "description": "Cash"}], "UpdateStatus": {"lastUpdateTime": "2020-10-30T00:22:13.1070500+00:00"}}, {"MegaDraftGroupId": 2, "MegaContestKey": "91482394", "MegaEntryKey": "2198813201", "UserName": "theprof02", "UserKey": "7686051", "UserMegaEntryCount": 0, "UserMegaEntryIndex": 0, "TimeRemainingOpponent": 0, "Rank": 3, "FantasyPoints": 1049.5, "FantasyPointsOpponent": 1188.82, "RankScore": 0, "RankScoreOpponent": 0, "UserNameOpponent": "sansbacon", "WinningValue": 20, "Winnings": [{"value": 20, "description": "Cash"}], "UpdateStatus": {"lastUpdateTime": "2020-10-30T00:22:13.1085953+00:00"}}, {"MegaDraftGroupId": 2, "MegaContestKey": "91482394", "MegaEntryKey": "2198821525", "UserName": "dakid456", "UserKey": "467189", "UserMegaEntryCount": 0, "UserMegaEntryIndex": 0, "TimeRemainingOpponent": 0, "Rank": 4, "FantasyPoints": 1037.98, "FantasyPointsOpponent": 1188.82, "RankScore": 0, "RankScoreOpponent": 0, "UserNameOpponent": "sansbacon", "WinningValue": 0, "UpdateStatus": {"lastUpdateTime": "2020-10-30T00:22:13.1078238+00:00"}}, {"MegaDraftGroupId": 2, "MegaContestKey": "91482394", "MegaEntryKey": "2198821540", "UserName": "deeps601", "UserKey": "2813709", "UserMegaEntryCount": 0, "UserMegaEntryIndex": 0, "TimeRemainingOpponent": 0, "Rank": 5, "FantasyPoints": 995.24, "FantasyPointsOpponent": 1188.82, "RankScore": 0, "RankScoreOpponent": 0, "UserNameOpponent": "sansbacon", "WinningValue": 0, "UpdateStatus": {"lastUpdateTime": "2020-10-30T00:22:13.1081971+00:00"}}, {"MegaDraftGroupId": 2, "MegaContestKey": "91482394", "MegaEntryKey": "2198813524", "UserName": "kcorbo7", "UserKey": "386560", "UserMegaEntryCount": 0, "UserMegaEntryIndex": 0, "TimeRemainingOpponent": 0, "Rank": 6, "FantasyPoints": 983.66, "FantasyPointsOpponent": 1188.82, "RankScore": 0, "RankScoreOpponent": 0, "UserNameOpponent": "sansbacon", "WinningValue": 0, "UpdateStatus": {"lastUpdateTime": "2020-10-30T00:22:13.1023989+00:00"}}, {"MegaDraftGroupId": 2, "MegaContestKey": "91482394", "MegaEntryKey": "2198839595", "UserName": "dmac266", "UserKey": "938411", "UserMegaEntryCount": 0, "UserMegaEntryIndex": 0, "TimeRemainingOpponent": 0, "Rank": 7, "FantasyPoints": 983.44, "FantasyPointsOpponent": 1188.82, "RankScore": 0, "RankScoreOpponent": 0, "UserNameOpponent": "sansbacon", "WinningValue": 0, "UpdateStatus": {"lastUpdateTime": "2020-10-30T00:22:13.1066754+00:00"}}, {"MegaDraftGroupId": 2, "MegaContestKey": "91482394", "MegaEntryKey": "2198831038", "UserName": "tylerhicks101", "UserKey": "9658590", "UserMegaEntryCount": 0, "UserMegaEntryIndex": 0, "TimeRemainingOpponent": 0, "Rank": 8, "FantasyPoints": 922.72, "FantasyPointsOpponent": 1188.82, "RankScore": 0, "RankScoreOpponent": 0, "UserNameOpponent": "sansbacon", "WinningValue": 0, "UpdateStatus": {"lastUpdateTime": "2020-10-30T00:22:13.1062652+00:00"}}, {"MegaDraftGroupId": 2, "MegaContestKey": "91482394", "MegaEntryKey": "2198839775", "UserName": "laidsy13", "UserKey": "6205160", "UserMegaEntryCount": 0, "UserMegaEntryIndex": 0, "TimeRemainingOpponent": 0, "Rank": 9, "FantasyPoints": 905.46, "FantasyPointsOpponent": 1188.82, "RankScore": 0, "RankScoreOpponent": 0, "UserNameOpponent": "sansbacon", "WinningValue": 0, "UpdateStatus": {"lastUpdateTime": "2020-10-30T00:22:13.1058446+00:00"}}, {"MegaDraftGroupId": 2, "MegaContestKey": "91482394", "MegaEntryKey": "2198821530", "UserName": "trace.martin77", "UserKey": "9942061", "UserMegaEntryCount": 0, "UserMegaEntryIndex": 0, "TimeRemainingOpponent": 0, "Rank": 10, "FantasyPoints": 887.58, "FantasyPointsOpponent": 1188.82, "RankScore": 0, "RankScoreOpponent": 0, "UserNameOpponent": "sansbacon", "WinningValue": 0, "UpdateStatus": {"lastUpdateTime": "2020-10-30T00:22:13.1053508+00:00"}}, {"MegaDraftGroupId": 2, "MegaContestKey": "91482394", "MegaEntryKey": "2198830791", "UserName": "chasewaters1001", "UserKey": "3571309", "UserMegaEntryCount": 0, "UserMegaEntryIndex": 0, "TimeRemainingOpponent": 0, "Rank": 11, "FantasyPoints": 856.66, "FantasyPointsOpponent": 1188.82, "RankScore": 0, "RankScoreOpponent": 0, "UserNameOpponent": "sansbacon", "WinningValue": 0, "UpdateStatus": {"lastUpdateTime": "2020-10-30T00:22:13.1073905+00:00"}}, {"MegaDraftGroupId": 2, "MegaContestKey": "91482394", "MegaEntryKey": "2198821382", "UserName": "MacADon529", "UserKey": "12956840", "UserMegaEntryCount": 0, "UserMegaEntryIndex": 0, "TimeRemainingOpponent": 0, "Rank": 12, "FantasyPoints": 843.36, "FantasyPointsOpponent": 1188.82, "RankScore": 0, "RankScoreOpponent": 0, "UserNameOpponent": "sansbacon", "WinningValue": 0, "UpdateStatus": {"lastUpdateTime": "2020-10-30T00:22:13.1022742+00:00"}}], "UpdateStatus": {"lastUpdateTime": "2020-10-30T00:22:13.1106540+00:00"}}